Workbook

Sheet Simulador
B5: ⚙️ CONFIGURAÇÕES PESSOAIS | F5: 📡 TAXAS DE MERCADO (REFERÊNCIA)
B6: Salário Mensal (R$) | D6: 2000 | F6: Taxa Selic (meta Copom, a.a.) | I6: 0.14
B7: Rendimento da Carteira (% a.m.) | D7: 0.006 | F7: CDI (a.a.) | I7: 0.139
B8: Sugestão de Investimento (30% do Salário) | D8: =D6*0.3 -> 600 | F8: IFIX – Yield Médio 10a (a.a.) | I8: 0.08
F9: Seu Rendimento Assumido (a.a.) | I9: =(1+D7)^12-1 -> 0.074424168
B10: 📈 PARÂMETROS DE INVESTIMENTO
B11: Quanto investir por mês? (R$) | D11: 200 | F11: 🎯 META FINANCEIRA
B12: Por quantos anos? | D12: 5 | F12: Valor da Meta (R$) | H12: 100000
B13: Taxa de Rendimento Mensal (%) | D13: 0.01079 | F13: Prazo Desejado (anos) | H13: 10
F14: Patrimônio Projetado no Prazo | H14: =D11*(((1+D13)^(H13*12)-1)/D13) -> 48656.843
B15: 🏆 RESULTADOS PROJETADOS | F15: Faltam para a Meta (R$) | H15: =MAX(H12-H14,0) -> 51343.157
B16: 💰 Patrimônio Acumulado (R$) | D16: =D11*((((1+D13)^(D12*12))-1)/D13) -> 16755.383 | F16: % da Meta Atingida | H16: =MIN(H14/H12,1) -> 0.48656843
B17: 📊 Dividendos Mensais Estimados (R$) | D17: =D16*D7 -> 100.5323 | F17: Tempo Necessário (anos) | H17: =LN(1+(H12*D13)/D11)/LN(1+D13)/12 -> 14.4077
B19: 🔭 CENÁRIOS DE PROJEÇÃO | F19: 🏢 FIIs REAIS SUGERIDOS (REFERÊNCIA)
B20: Prazo | C20: Patrimônio (R$) | D20: Dividendos/mês (R$) | F20: Ticker | G20: Segmento | H20: DY 12m | I20: P/VP | J20: Cotação (R$) | K20: Valor Investido (R$) | L20: Qtd. Cotas
B21: 2 anos | C21: =D11*((((1+D13)^(2*12))-1)/D13) -> 5445.5255 | D21: =C21*D7 -> 32.673153 | F21: MXRF11 | G21: Papel (CRI) | H21: 0.1221 | I21: 1 | J21: 9.19 | K21: 0 | L21: =IFERROR(K21/J21,0) -> 0
B22: 5 anos | C22: =D11*((((1+D13)^(5*12))-1)/D13) -> 16755.383 | D22: =C22*D7 -> 100.5323 | F22: HGLG11 | G22: Tijolo (Logística) | H22: 0.0899 | I22: 0.89 | J22: 148.3 | K22: 0 | L22: =IFERROR(K22/J22,0) -> 0
B23: 10 anos | C23: =D11*((((1+D13)^(10*12))-1)/D13) -> 48656.843 | D23: =C23*D7 -> 291.94106 | F23: KNRI11 | G23: Híbrido | H23: 0.0829 | I23: 0.97 | J23: 158.23 | K23: 0 | L23: =IFERROR(K23/J23,0) -> 0
B24: 20 anos | C24: =D11*((((1+D13)^(20*12))-1)/D13) -> 225039.68 | D24: =C24*D7 -> 1350.2381 | F24: XPML11 | G24: Tijolo (Shoppings) | H24: 0.1059 | I24: 0.95 | J24: 104.38 | K24: 0 | L24: =IFERROR(K24/J24,0) -> 0
B25: 30 anos | C25: =D11*((((1+D13)^(30*12))-1)/D13) -> 864433.93 | D25: =C25*D7 -> 5186.6036 | F25: TOTAL INVESTIDO | K25: =SUM(K21:K24) -> 0 | L25: =SUM(L21:L24) -> 0
F26: Dados de mercado sujeitos a variação diária. Não é recomendação de investimento.
B28: 🧩 PERFIL DE INVESTIDOR & ALOCAÇÃO DE FIIs
B29: Perfil do Investidor | D29: Moderado
B30: Valor a Investir por Mês (R$) | D30: =D11 -> 200
B32: Tipo de FII | C32: % Sugerido | D32: Valor (R$)
B33: PAPEL | C33: =IFERROR(INDEX(Dados!$D:$D,MATCH(D29&"-"&B33,Dados!$A:$A,0)),0) -> 0.32 | D33: =C33*D30 -> 64
B34: TIJOLO | C34: =IFERROR(INDEX(Dados!$D:$D,MATCH(D29&"-"&B34,Dados!$A:$A,0)),0) -> 0.35 | D34: =C34*D30 -> 70
B35: HÍBRIDOS | C35: =IFERROR(INDEX(Dados!$D:$D,MATCH(D29&"-"&B35,Dados!$A:$A,0)),0) -> 0.08 | D35: =C35*D30 -> 16
B36: FOFs | C36: =IFERROR(INDEX(Dados!$D:$D,MATCH(D29&"-"&B36,Dados!$A:$A,0)),0) -> 0.05 | D36: =C36*D30 -> 10
B37: DESENVOLVIMENTO | C37: =IFERROR(INDEX(Dados!$D:$D,MATCH(D29&"-"&B37,Dados!$A:$A,0)),0) -> 0.1 | D37: =C37*D30 -> 20
B38: HOTELARIAS | C38: =IFERROR(INDEX(Dados!$D:$D,MATCH(D29&"-"&B38,Dados!$A:$A,0)),0) -> 0.1 | D38: =C38*D30 -> 20
B39: TOTAL ALOCADO | C39: =SUM(C33:C38) -> 1 | D39: =SUM(D33:D38) -> 200
B41: IC Financial Simulator · Igor Cardoso · github.com/igorcardoso

Sheet Dados
A1: 🗂 BASE DE DADOS — Alocação por Perfil de Investidor
A2: CHAVE | B2: PERFIL | C2: TIPO DE FII | D2: %
A3: Conservador-PAPEL | B3: Conservador | C3: PAPEL | D3: 0.3
A4: Conservador-TIJOLO | B4: Conservador | C4: TIJOLO | D4: 0.5
A5: Conservador-HÍBRIDOS | B5: Conservador | C5: HÍBRIDOS | D5: 0.1
A6: Conservador-FOFs | B6: Conservador | C6: FOFs | D6: 0.1
A7: Conservador-DESENVOLVIMENTO | B7: Conservador | C7: DESENVOLVIMENTO | D7: 0
A8: Conservador-HOTELARIAS | B8: Conservador | C8: HOTELARIAS | D8: 0
A9: Moderado-PAPEL | B9: Moderado | C9: PAPEL | D9: 0.32
A10: Moderado-TIJOLO | B10: Moderado | C10: TIJOLO | D10: 0.35
A11: Moderado-HÍBRIDOS | B11: Moderado | C11: HÍBRIDOS | D11: 0.08
A12: Moderado-FOFs | B12: Moderado | C12: FOFs | D12: 0.05
A13: Moderado-DESENVOLVIMENTO | B13: Moderado | C13: DESENVOLVIMENTO | D13: 0.1
A14: Moderado-HOTELARIAS | B14: Moderado | C14: HOTELARIAS | D14: 0.1
... A20: Agressivo-HOTELARIAS | B20: Agressivo | C20: HOTELARIAS | D20: 0.1

Sheet Guia Rápido
B4: 1️⃣ Salário & Rendimento
B5: 2️⃣ Parâmetros de Investimento
B6: 3️⃣ Leia os Resultados
B7: 4️⃣ Cenários Automáticos
B8: 5️⃣ Perfil & Alocação
B9: D29 → escolha seu perfil via lista suspensa (Conservador / Moderado / Agressivo). A tabela de FIIs mostra o % sugerido para cada tipo e o valor em R$.
B15: 📐 FÓRMULAS UTILIZADAS
B16: Juros Compostos (Patrimônio) | C16: PMT × [((1 + i)^n − 1) / i] onde i = taxa mensal, n = meses
B17: Dividendos Mensais | C17: Patrimônio × Rendimento da Carteira (mensal)
B18: Sugestão de Investimento | C18: 30% do Salário Mensal
B19: Alocação por FII | C19: % do Perfil × Valor mensal a investir
